probsamplers/__init__.py
probsamplers/aux/__init__.py
probsamplers/aux/funcs.py
probsamplers/aux/structs.py
probsamplers/distributions/__init__.py
probsamplers/distributions/mvn.py
probsamplers/distributions/targets.py
probsamplers/mcmc/__init__.py
probsamplers/mcmc/mcmc.py
probsamplers-0.1.0.dist-info/LICENSE
probsamplers-0.1.0.dist-info/METADATA
probsamplers-0.1.0.dist-info/WHEEL
probsamplers-0.1.0.dist-info/top_level.txt
probsamplers-0.1.0.dist-info/RECORD
