Metadata-Version: 2.1
Name: probsamplers
Version: 0.1.0
Summary: JupyterLab version of mcmc-demo
Home-page: https://rgoswami.me
Author: Rohit Goswami
Author-email: Rohit Goswami <rog32@hi.is>
License: MIT
Project-URL: Homepage, https://github.com/HaoZeke/probsamplers
Project-URL: Bug Tracker, https://github.com/HaoZeke/probsamplers/issues
Requires-Python: >3.10
License-File: LICENSE
Requires-Dist: numpy
Requires-Dist: scipy
Provides-Extra: plotting
Requires-Dist: matplotlib (>=2.2.0) ; extra == 'plotting'
Requires-Dist: jupyter ; extra == 'plotting'
